README.txt
setup.py
collective/__init__.py
collective.portlet.recentcomments.egg-info/PKG-INFO
collective.portlet.recentcomments.egg-info/SOURCES.txt
collective.portlet.recentcomments.egg-info/dependency_links.txt
collective.portlet.recentcomments.egg-info/entry_points.txt
collective.portlet.recentcomments.egg-info/namespace_packages.txt
collective.portlet.recentcomments.egg-info/not-zip-safe
collective.portlet.recentcomments.egg-info/requires.txt
collective.portlet.recentcomments.egg-info/top_level.txt
collective/portlet/__init__.py
collective/portlet/recentcomments/__init__.py
collective/portlet/recentcomments/recentcommentsportlet.py
collective/portlet/recentcomments/tests/__init__.py
collective/portlet/recentcomments/tests/base.py
collective/portlet/recentcomments/tests/test_portlet.py