Metadata-Version: 1.0
Name: collective.portlet.recentcomments
Version: 1.0
Summary: Recent Comment Portlet
Home-page: http://ediaz.me
Author: Eduardo Diaz
Author-email: ediaz@ediaz.me
License: GPL
Keywords: recent comments portlet
Platform: UNKNOWN
Classifier: Framework :: Plone
Classifier: Programming Language :: Python
